{"_type":"export","__export_format":4,"__export_date":"2022-06-05T00:11:02.626Z","__export_source":"insomnia.desktop.app:v2021.7.2","resources":[{"_id":"req_f793ec82a2ae4c018e28d89368d29458","parentId":"fld_c3bf9388bd8f483d9ec954f268caf69f","modified":1654376259977,"created":1653526165757,"url":"{{ _.base_uri }}/leagues","name":"/","description":"","method":"GET","body":{},"parameters":[],"headers":[],"authentication":{},"metaSortKey":-1653526165758,"isPrivate":false,"settingStoreCookies":true,"settingSendCookies":true,"settingDisableRenderRequestBody":false,"settingEncodeUrl":true,"settingRebuildPath":true,"settingFollowRedirects":"global","_type":"request"},{"_id":"fld_c3bf9388bd8f483d9ec954f268caf69f","parentId":"wrk_215ff36b908a45a09c95b245f0ff0512","modified":1654384477191,"created":1653526134578,"name":"/leagues","description":"","environment":{},"environmentPropertyOrder":{},"metaSortKey":-1653527807422,"_type":"request_group"},{"_id":"wrk_215ff36b908a45a09c95b245f0ff0512","parentId":null,"modified":1653161206740,"created":1645708030634,"name":"Back-End-CBV-Manager","description":"","scope":"collection","_type":"workspace"},{"_id":"req_a138cd9983754e21b8cec31719d9813c","parentId":"fld_c3bf9388bd8f483d9ec954f268caf69f","modified":1654383178524,"created":1653526330327,"url":"{{ _.base_uri }}/leagues/1","name":"/{league_id}","description":"","method":"GET","body":{},"parameters":[],"headers":[],"authentication":{},"metaSortKey":-1653526165708,"isPrivate":false,"settingStoreCookies":true,"settingSendCookies":true,"settingDisableRenderRequestBody":false,"settingEncodeUrl":true,"settingRebuildPath":true,"settingFollowRedirects":"global","_type":"request"},{"_id":"req_dd0b93ecaaa44c63a13c5764284e08a6","parentId":"fld_c3bf9388bd8f483d9ec954f268caf69f","modified":1654386575340,"created":1653526704608,"url":"{{ _.base_uri }}/leagues","name":"/","description":"","method":"POST","body":{"mimeType":"application/x-www-form-urlencoded","params":[{"id":"pair_cd5deea7a34848a79e9e851dec20b7b5","name":"title","value":"Super Liga de Volei","description":""},{"id":"pair_f8cd3b9f3d054b10a5f737a1b967523b","name":"year","value":"2022","description":""},{"id":"pair_fc9dd7603f5847b0a6420a7727e20ae3","name":"category","value":"MALE","description":""},{"id":"pair_497bc2e92ad54b9b95ab7959035856dd","name":"begin_in","value":"2022-05-30","description":""},{"id":"pair_bebec4eaed0b4962b21f65d90a33edc5","name":"classificatory_limit","value":"2022-06-30","description":""},{"id":"pair_d4cd19c1196c4e82babc2caa2624ea8c","name":"quarter_finals_limit","value":"2022-10-15","description":""},{"id":"pair_b226d595c1c440ef8946189f4878e335","name":"semifinals_limit","value":"2022-11-10","description":""},{"id":"pair_2b4591dcf6c94c06a7f8bd0b900d3e31","name":"finish_in","value":"2022-11-25","description":""}]},"parameters":[],"headers":[{"name":"Content-Type","value":"application/x-www-form-urlencoded","id":"pair_5bf7ad7a32b7434f9598750e59cc421e"}],"authentication":{},"metaSortKey":-1653526165658,"isPrivate":false,"settingStoreCookies":true,"settingSendCookies":true,"settingDisableRenderRequestBody":false,"settingEncodeUrl":true,"settingRebuildPath":true,"settingFollowRedirects":"global","_type":"request"},{"_id":"req_5707bdcc9cee46d69be568699ddcb081","parentId":"fld_c3bf9388bd8f483d9ec954f268caf69f","modified":1654383464668,"created":1653527701510,"url":"{{ _.base_uri }}/leagues/1","name":"/{league_id}","description":"","method":"PUT","body":{"mimeType":"application/x-www-form-urlencoded","params":[{"id":"pair_cd5deea7a34848a79e9e851dec20b7b5","name":"title","value":"Super Liga de Volei","description":""},{"id":"pair_f8cd3b9f3d054b10a5f737a1b967523b","name":"year","value":"2021","description":""},{"id":"pair_fc9dd7603f5847b0a6420a7727e20ae3","name":"category","value":"FEMALE","description":""},{"id":"pair_497bc2e92ad54b9b95ab7959035856dd","name":"begin_in","value":"2022-05-30","description":""},{"id":"pair_bebec4eaed0b4962b21f65d90a33edc5","name":"classificatory_limit","value":"2022-06-30","description":""},{"id":"pair_d4cd19c1196c4e82babc2caa2624ea8c","name":"quarter_finals_limit","value":"2022-10-15","description":""},{"id":"pair_b226d595c1c440ef8946189f4878e335","name":"semifinals_limit","value":"2022-11-10","description":""},{"id":"pair_2b4591dcf6c94c06a7f8bd0b900d3e31","name":"finish_in","value":"2022-11-25","description":""}]},"parameters":[],"headers":[{"name":"Content-Type","value":"application/x-www-form-urlencoded","id":"pair_5bf7ad7a32b7434f9598750e59cc421e"}],"authentication":{},"metaSortKey":-1653348559272.5,"isPrivate":false,"settingStoreCookies":true,"settingSendCookies":true,"settingDisableRenderRequestBody":false,"settingEncodeUrl":true,"settingRebuildPath":true,"settingFollowRedirects":"global","_type":"request"},{"_id":"req_fb1689c2e12e4d0286318e7c63c2f385","parentId":"fld_c3bf9388bd8f483d9ec954f268caf69f","modified":1654383194695,"created":1653527755034,"url":"{{ _.base_uri }}/leagues/1","name":"/{league_id}","description":"","method":"DELETE","body":{},"parameters":[],"headers":[],"authentication":{},"metaSortKey":-1653348559222.5,"isPrivate":false,"settingStoreCookies":true,"settingSendCookies":true,"settingDisableRenderRequestBody":false,"settingEncodeUrl":true,"settingRebuildPath":true,"settingFollowRedirects":"global","_type":"request"},{"_id":"req_eca4f5be1bfd4f39bda7a73f0969943f","parentId":"fld_6d952f118d2c44978dd05c055af39613","modified":1654385583959,"created":1653159941233,"url":"{{ _.base_uri }}/leagues/1/teams","name":"/","description":"","method":"GET","body":{},"parameters":[],"headers":[],"authentication":{},"metaSortKey":-1653158714703,"isPrivate":false,"settingStoreCookies":true,"settingSendCookies":true,"settingDisableRenderRequestBody":false,"settingEncodeUrl":true,"settingRebuildPath":true,"settingFollowRedirects":"global","_type":"request"},{"_id":"fld_6d952f118d2c44978dd05c055af39613","parentId":"fld_c3bf9388bd8f483d9ec954f268caf69f","modified":1654383819920,"created":1653158697018,"name":"/teams","description":"","environment":{},"environmentPropertyOrder":{},"metaSortKey":-1653348559172.5,"_type":"request_group"},{"_id":"req_5f395fbc35634fdeaa37760f8df8d79d","parentId":"fld_6d952f118d2c44978dd05c055af39613","modified":1654385857399,"created":1653159466486,"url":"{{ _.base_uri }}/leagues/1/teams/1","name":"/{team_id}","description":"","method":"GET","body":{},"parameters":[],"headers":[],"authentication":{},"metaSortKey":-1653158714653,"isPrivate":false,"settingStoreCookies":true,"settingSendCookies":true,"settingDisableRenderRequestBody":false,"settingEncodeUrl":true,"settingRebuildPath":true,"settingFollowRedirects":"global","_type":"request"},{"_id":"req_b07a716921e541c58924461438d67317","parentId":"fld_6d952f118d2c44978dd05c055af39613","modified":1654386422359,"created":1653158714603,"url":"{{ _.base_uri }}/leagues/1/teams","name":"/","description":"","method":"POST","body":{"mimeType":"application/x-www-form-urlencoded","params":[{"id":"pair_dc91a47c82054d6bb2ab3ad7825a5c45","name":"name","value":"Sada Cruzeiro Vôlei","description":""},{"id":"pair_971cdbb55f454f1280a10570bdf91e43","name":"year_foundation","value":"2006","description":""},{"id":"pair_13ea027dca664d2ab7ac3e23c07ba02b","name":"gymnasium","value":"Poliesportivo do Riacho","description":""},{"id":"pair_ca67df4873ee4d1194f3240a46f3a561","name":"category","value":"MALE","description":""},{"id":"pair_c4394321b83c4164811e493d924dbce7","name":"affiliated_federation_in","value":"2022-01-01","description":""}]},"parameters":[],"headers":[{"name":"Content-Type","value":"application/x-www-form-urlencoded","id":"pair_2dacf57103bc4e2d84577ff8b6ea5200"},{"id":"pair_f2b120a48c544b2f86c2d6c48777dc38","name":"Accept","value":"application/json","description":"","disabled":true}],"authentication":{},"metaSortKey":-1653158714603,"isPrivate":false,"settingStoreCookies":true,"settingSendCookies":true,"settingDisableRenderRequestBody":false,"settingEncodeUrl":true,"settingRebuildPath":true,"settingFollowRedirects":"global","_type":"request"},{"_id":"req_fa8ea478ae74450cb39083148daf2ab6","parentId":"fld_6d952f118d2c44978dd05c055af39613","modified":1654386013061,"created":1653159580062,"url":"{{ _.base_uri }}/leagues/1/teams/1","name":"/{team_id}","description":"","method":"PUT","body":{"mimeType":"application/x-www-form-urlencoded","params":[{"id":"pair_dc91a47c82054d6bb2ab3ad7825a5c45","name":"name","value":"Sada Cruzeiro Vôlei","description":""},{"id":"pair_971cdbb55f454f1280a10570bdf91e43","name":"year_foundation","value":"2006","description":""},{"id":"pair_13ea027dca664d2ab7ac3e23c07ba02b","name":"gymnasium","value":"Poliesportivo do Riacho","description":""},{"id":"pair_ca67df4873ee4d1194f3240a46f3a561","name":"category","value":"FEMALE","description":""}]},"parameters":[],"headers":[{"name":"Content-Type","value":"application/x-www-form-urlencoded","id":"pair_2dacf57103bc4e2d84577ff8b6ea5200"}],"authentication":{},"metaSortKey":-1651005531069.5,"isPrivate":false,"settingStoreCookies":true,"settingSendCookies":true,"settingDisableRenderRequestBody":false,"settingEncodeUrl":true,"settingRebuildPath":true,"settingFollowRedirects":"global","_type":"request"},{"_id":"req_88f3ce04f6a04ae7b0efac6684781892","parentId":"fld_6d952f118d2c44978dd05c055af39613","modified":1654384604532,"created":1653159817548,"url":"{{ _.base_uri }}/leagues/1/teams/1","name":"/{team_id}","description":"","method":"DELETE","body":{},"parameters":[],"headers":[],"authentication":{},"metaSortKey":-1649928939302.75,"isPrivate":false,"settingStoreCookies":true,"settingSendCookies":true,"settingDisableRenderRequestBody":false,"settingEncodeUrl":true,"settingRebuildPath":true,"settingFollowRedirects":"global","_type":"request"},{"_id":"req_1b2910b4cc394d238586c70797c72f61","parentId":"fld_3f74e952d82b42a39d3978448053fcc0","modified":1654386562535,"created":1653169487795,"url":"{{ _.base_uri }}/leagues/1/teams/1/technical_committee","name":"/","description":"","method":"GET","body":{},"parameters":[],"headers":[],"authentication":{},"metaSortKey":-1653170952887,"isPrivate":false,"settingStoreCookies":true,"settingSendCookies":true,"settingDisableRenderRequestBody":false,"settingEncodeUrl":true,"settingRebuildPath":true,"settingFollowRedirects":"global","_type":"request"},{"_id":"fld_3f74e952d82b42a39d3978448053fcc0","parentId":"fld_6d952f118d2c44978dd05c055af39613","modified":1654386084126,"created":1653169400718,"name":"/technical_committee","description":"","environment":{},"environmentPropertyOrder":{},"metaSortKey":-1649928939290.25,"_type":"request_group"},{"_id":"req_81cc5d619a2a4283a22809865eaaff1b","parentId":"fld_3f74e952d82b42a39d3978448053fcc0","modified":1654386718108,"created":1653170952837,"url":"{{ _.base_uri }}/leagues/1/teams/1/technical_committee","name":"/","description":"","method":"POST","body":{"mimeType":"application/x-www-form-urlencoded","params":[{"name":"coach","value":"Felipe Ferraz","id":"pair_ff074a6ac04f4f2ab69b81be8a9cf820"},{"id":"pair_25f08e20861d44648370bc53f7a8b19d","name":"coach_assistant","value":"Beto Martelete","description":""},{"id":"pair_7b8df4347b45488da1801a3f0a5aa607","name":"supervisor","value":"Luís Carlos Sales","description":""},{"id":"pair_62478c4c42f2475398bb22e399488581","name":"personal_trainer","value":"Fabio Correia","description":""},{"id":"pair_40152c598ea645a9b5caa2c9b408e7be","name":"physiotherapist","value":"Alysson Zuin","description":""},{"id":"pair_09111110446743559facd7d0b9aee285","name":"masseuse","value":"Willian Cunha","description":""},{"id":"pair_fde30fe8a2404a25b799b65739f5ec62","name":"doctor","value":"Sérgio Campolina","description":""}]},"parameters":[],"headers":[{"name":"Content-Type","value":"application/x-www-form-urlencoded","id":"pair_7c08cb26aa214d6fa817ee9cae7f6acb"}],"authentication":{},"metaSortKey":-1653170952837,"isPrivate":false,"settingStoreCookies":true,"settingSendCookies":true,"settingDisableRenderRequestBody":false,"settingEncodeUrl":true,"settingRebuildPath":true,"settingFollowRedirects":"global","_type":"request"},{"_id":"req_c40dd9cf311f4748b47dba4842628685","parentId":"fld_3f74e952d82b42a39d3978448053fcc0","modified":1654386899643,"created":1653171955555,"url":"{{ _.base_uri }}/leagues/1/teams/1/technical_committee","name":"/","description":"","method":"PUT","body":{"mimeType":"application/x-www-form-urlencoded","params":[{"name":"coach","value":"Felipe Ferras","id":"pair_ff074a6ac04f4f2ab69b81be8a9cf820"},{"id":"pair_25f08e20861d44648370bc53f7a8b19d","name":"coach_assistant","value":"Beto Marteleteeee","description":""},{"id":"pair_7b8df4347b45488da1801a3f0a5aa607","name":"supervisor","value":"Luís Carlos Sales","description":""},{"id":"pair_62478c4c42f2475398bb22e399488581","name":"personal_trainer","value":"Fabio Correia","description":""},{"id":"pair_40152c598ea645a9b5caa2c9b408e7be","name":"physiotherapist","value":"Alysson Zuin","description":""},{"id":"pair_09111110446743559facd7d0b9aee285","name":"masseuse","value":"Willian Cunha","description":""},{"id":"pair_fde30fe8a2404a25b799b65739f5ec62","name":"doctor","value":"Sérgio Campolina","description":""}]},"parameters":[],"headers":[{"name":"Content-Type","value":"application/x-www-form-urlencoded","id":"pair_7c08cb26aa214d6fa817ee9cae7f6acb"}],"authentication":{},"metaSortKey":-1653168047479.5,"isPrivate":false,"settingStoreCookies":true,"settingSendCookies":true,"settingDisableRenderRequestBody":false,"settingEncodeUrl":true,"settingRebuildPath":true,"settingFollowRedirects":"global","_type":"request"},{"_id":"req_8cdccc33a4804657bd138ec968a13101","parentId":"fld_3f74e952d82b42a39d3978448053fcc0","modified":1654386897093,"created":1653171994974,"url":"{{ _.base_uri }}/leagues/1/teams/1/technical_committee","name":"/","description":"","method":"DELETE","body":{},"parameters":[],"headers":[],"authentication":{},"metaSortKey":-1653166594800.75,"isPrivate":false,"settingStoreCookies":true,"settingSendCookies":true,"settingDisableRenderRequestBody":false,"settingEncodeUrl":true,"settingRebuildPath":true,"settingFollowRedirects":"global","_type":"request"},{"_id":"req_36ece9e8e63049399d555fbefba647fa","parentId":"fld_5ec4cc050dad46bf91dee8b828fd3e29","modified":1654387330055,"created":1653527824106,"url":"{{ _.base_uri }}/leagues/1/teams/1/players","name":"/","description":"","method":"GET","body":{},"parameters":[],"headers":[],"authentication":{},"metaSortKey":-1653529316460,"isPrivate":false,"settingStoreCookies":true,"settingSendCookies":true,"settingDisableRenderRequestBody":false,"settingEncodeUrl":true,"settingRebuildPath":true,"settingFollowRedirects":"global","_type":"request"},{"_id":"fld_5ec4cc050dad46bf91dee8b828fd3e29","parentId":"fld_6d952f118d2c44978dd05c055af39613","modified":1654386081611,"created":1653527807372,"name":"/players","description":"","environment":{},"environmentPropertyOrder":null,"metaSortKey":-1649928939277.75,"_type":"request_group"},{"_id":"req_ce58106303b64f7cad1d6e09d12210a3","parentId":"fld_5ec4cc050dad46bf91dee8b828fd3e29","modified":1654387519838,"created":1653528709551,"url":"{{ _.base_uri }}/leagues/1/teams/1/players/2","name":"/{player_id}","description":"","method":"GET","body":{},"parameters":[],"headers":[],"authentication":{},"metaSortKey":-1653529316435,"isPrivate":false,"settingStoreCookies":true,"settingSendCookies":true,"settingDisableRenderRequestBody":false,"settingEncodeUrl":true,"settingRebuildPath":true,"settingFollowRedirects":"global","_type":"request"},{"_id":"req_5725bf4cc5fe4a1ea2a4e92f147a587a","parentId":"fld_5ec4cc050dad46bf91dee8b828fd3e29","modified":1654387509971,"created":1653529316410,"url":"{{ _.base_uri }}/leagues/1/teams/1/players","name":"/","description":"","method":"POST","body":{"mimeType":"application/x-www-form-urlencoded","params":[{"id":"pair_dfd00af8ab794f3caef35b928f5f391e","name":"name","value":"Mateus","description":""},{"id":"pair_f19a8554ffff4c8dafe780fc80b83a8f","name":"birthday","value":"1985-03-20","description":""},{"id":"pair_05d9be957d364c0bb5485f88059d3025","name":"document","value":"123456789","description":""},{"id":"pair_5bcf15da18ea4f609ff1f2efd2f637bc","name":"shirt_number","value":"1","description":""}]},"parameters":[],"headers":[{"name":"Content-Type","value":"application/x-www-form-urlencoded","id":"pair_d9ea2bef07f042058278415eb28bdda6"}],"authentication":{},"metaSortKey":-1653529316410,"isPrivate":false,"settingStoreCookies":true,"settingSendCookies":true,"settingDisableRenderRequestBody":false,"settingEncodeUrl":true,"settingRebuildPath":true,"settingFollowRedirects":"global","_type":"request"},{"_id":"req_e866b4a143f94fdfa8a3483b616a09aa","parentId":"fld_5ec4cc050dad46bf91dee8b828fd3e29","modified":1654387675038,"created":1653528856843,"url":"{{ _.base_uri }}/leagues/1/teams/1/players/2","name":"/{player_id}","description":"","method":"PUT","body":{"mimeType":"application/x-www-form-urlencoded","params":[{"id":"pair_ec25b400f8ed430ca3afb750ef7dcadc","name":"name","value":"Lucarelli","description":""},{"id":"pair_8ef4bb9dc14248b7b9209c6c061bad4a","name":"birthday","value":"1990-05-26","description":""}]},"parameters":[],"headers":[{"name":"Content-Type","value":"application/x-www-form-urlencoded","id":"pair_dfc45824bd9c4e6bbf1983887dfecf6b"}],"authentication":{},"metaSortKey":-1653529090046.5,"isPrivate":false,"settingStoreCookies":true,"settingSendCookies":true,"settingDisableRenderRequestBody":false,"settingEncodeUrl":true,"settingRebuildPath":true,"settingFollowRedirects":"global","_type":"request"},{"_id":"req_40ebf92cfe4842fea651949861b42987","parentId":"fld_5ec4cc050dad46bf91dee8b828fd3e29","modified":1654387731458,"created":1653528863683,"url":"{{ _.base_uri }}/leagues/1/teams/1/players/1","name":"/{player_id}","description":"","method":"DELETE","body":{},"parameters":[],"headers":[],"authentication":{},"metaSortKey":-1653528863683,"isPrivate":false,"settingStoreCookies":true,"settingSendCookies":true,"settingDisableRenderRequestBody":false,"settingEncodeUrl":true,"settingRebuildPath":true,"settingFollowRedirects":"global","_type":"request"},{"_id":"req_b0701fedde594a1888b282ed1279ff44","parentId":"fld_553d010b50a54e718390dd10caca3bf6","modified":1653531374238,"created":1653531125468,"url":"{{ _.base_uri }}/positions","name":"/","description":"","method":"GET","body":{},"parameters":[],"headers":[],"authentication":{},"metaSortKey":-1653529316460,"isPrivate":false,"settingStoreCookies":true,"settingSendCookies":true,"settingDisableRenderRequestBody":false,"settingEncodeUrl":true,"settingRebuildPath":true,"settingFollowRedirects":"global","_type":"request"},{"_id":"fld_553d010b50a54e718390dd10caca3bf6","parentId":"wrk_215ff36b908a45a09c95b245f0ff0512","modified":1653531125442,"created":1653531125442,"name":"/positions","description":"","environment":{},"environmentPropertyOrder":null,"metaSortKey":-1653343252245,"_type":"request_group"},{"_id":"req_254df121e22044b8b5e0eb07e9852033","parentId":"fld_553d010b50a54e718390dd10caca3bf6","modified":1653532473271,"created":1653531125472,"url":"{{ _.base_uri }}/positions/1","name":"/{position_id}","description":"","method":"GET","body":{},"parameters":[],"headers":[],"authentication":{},"metaSortKey":-1653529316435,"isPrivate":false,"settingStoreCookies":true,"settingSendCookies":true,"settingDisableRenderRequestBody":false,"settingEncodeUrl":true,"settingRebuildPath":true,"settingFollowRedirects":"global","_type":"request"},{"_id":"req_464a22a6858048e8b3ac98d95d6d3ec7","parentId":"fld_553d010b50a54e718390dd10caca3bf6","modified":1653532058772,"created":1653531125485,"url":"{{ _.base_uri }}/positions","name":"/","description":"","method":"POST","body":{"mimeType":"application/x-www-form-urlencoded","params":[{"id":"pair_dabcb2c6aad145d99c8b6630443a78d9","name":"name","value":"Ala","description":""}]},"parameters":[],"headers":[{"name":"Content-Type","value":"application/x-www-form-urlencoded","id":"pair_d9ea2bef07f042058278415eb28bdda6"}],"authentication":{},"metaSortKey":-1653529316410,"isPrivate":false,"settingStoreCookies":true,"settingSendCookies":true,"settingDisableRenderRequestBody":false,"settingEncodeUrl":true,"settingRebuildPath":true,"settingFollowRedirects":"global","_type":"request"},{"_id":"req_a399b02db65249efbd5454000cbf1f2e","parentId":"fld_553d010b50a54e718390dd10caca3bf6","modified":1653532523333,"created":1653531125476,"url":"{{ _.base_uri }}/positions/1","name":"/{position_id}","description":"","method":"PUT","body":{"mimeType":"application/x-www-form-urlencoded","params":[{"id":"pair_53ff62f94b024f048e5b9dbcadcaa7a5","name":"name","value":"Levantador","description":""}]},"parameters":[],"headers":[{"name":"Content-Type","value":"application/x-www-form-urlencoded","id":"pair_d768ebc1195d4e708f17e950594c1f3e"}],"authentication":{},"metaSortKey":-1653529090046.5,"isPrivate":false,"settingStoreCookies":true,"settingSendCookies":true,"settingDisableRenderRequestBody":false,"settingEncodeUrl":true,"settingRebuildPath":true,"settingFollowRedirects":"global","_type":"request"},{"_id":"req_620ea8b5b69d4f10bfed7411c03d4f5b","parentId":"fld_553d010b50a54e718390dd10caca3bf6","modified":1653534471736,"created":1653531125481,"url":"{{ _.base_uri }}/positions/1","name":"/{position_id}","description":"","method":"DELETE","body":{},"parameters":[],"headers":[],"authentication":{},"metaSortKey":-1653528863683,"isPrivate":false,"settingStoreCookies":true,"settingSendCookies":true,"settingDisableRenderRequestBody":false,"settingEncodeUrl":true,"settingRebuildPath":true,"settingFollowRedirects":"global","_type":"request"},{"_id":"env_e169a43d5e1540d928ac7612c9c2b4fd4f0a7176","parentId":"wrk_215ff36b908a45a09c95b245f0ff0512","modified":1653166807218,"created":1645708030642,"name":"Base Environment","data":{"base_uri":"http://"},"dataPropertyOrder":{"&":["base_uri"]},"color":null,"isPrivate":false,"metaSortKey":1645708030642,"_type":"environment"},{"_id":"jar_e169a43d5e1540d928ac7612c9c2b4fd4f0a7176","parentId":"wrk_215ff36b908a45a09c95b245f0ff0512","modified":1653159039303,"created":1645708030646,"name":"Default Jar","cookies":[{"key":"pga4_session","value":"189e2034-cb43-44d2-9ddd-49b1c141262d!qOfOj/h7DfJ84Bw2LRszRo//Zeg=","expires":"2022-03-09T22:23:29.000Z","domain":"localhost","path":"/","httpOnly":true,"extensions":["SameSite=Lax"],"hostOnly":true,"creation":"2022-03-06T14:45:20.034Z","lastAccessed":"2022-03-08T22:23:29.498Z","id":"8177807257400846"},{"key":"laravel_session","value":"eyJpdiI6ImRiUDhIdkdnbXlmODlucXNYL05GdHc9PSIsInZhbHVlIjoiakxBS1hRazBaSHFBSmJQWStRbnRBOUkrVmlLT1hVZWlXTVM1Sk5rRVBHQWhHOTdtUDFCM2pub2NXb2xqVWdkMEFOUzRSbDMvSU1NeWRYcFNSWkk2cEVDMTF6bDdlcTBJNjlxckVvVEF3VUZua0V2bnB3enViK3dIekYrSHlaa3ciLCJtYWMiOiIwMThiZjkzYzdiODEzZTM1NDU3MDY3YjJiMDA0MzBkMDI0NDIzOTQzMTIwODQxYjVhNzllNGY1ZTY5N2Y2YTY3IiwidGFnIjoiIn0%3D","expires":"2022-05-21T20:50:39.000Z","maxAge":7200,"domain":"127.0.0.1","path":"/","httpOnly":true,"extensions":["samesite=lax"],"hostOnly":true,"creation":"2022-05-21T18:46:08.873Z","lastAccessed":"2022-05-21T18:50:39.302Z","id":"44134208493698734"}],"_type":"cookie_jar"},{"_id":"spc_b040afd199c647f78c2bb979b6aa8293","parentId":"wrk_215ff36b908a45a09c95b245f0ff0512","modified":1645708030635,"created":1645708030635,"fileName":"AWS Api Gateway","contents":"","contentType":"yaml","_type":"api_spec"},{"_id":"env_a87edd42e5da44c8bb876f2cc47efeac","parentId":"env_e169a43d5e1540d928ac7612c9c2b4fd4f0a7176","modified":1653534498120,"created":1653166742921,"name":"Produção","data":{"base_uri":"https://cbv-manager.herokuapp.com/api"},"dataPropertyOrder":{"&":["base_uri"]},"color":"#ff0000","isPrivate":false,"metaSortKey":1,"_type":"environment"},{"_id":"env_1908abc161b24a76bfdd77fab97850e2","parentId":"env_e169a43d5e1540d928ac7612c9c2b4fd4f0a7176","modified":1654384384441,"created":1653166769891,"name":"Local","data":{"base_uri":"http://127.0.0.1:8000/api"},"dataPropertyOrder":{"&":["base_uri"]},"color":"#00ff6e","isPrivate":false,"metaSortKey":0,"_type":"environment"}]}